biosimulators_pysces/__init__.py
biosimulators_pysces/__main__.py
biosimulators_pysces/_version.py
biosimulators_pysces/core.py
biosimulators_pysces/data_model.py
biosimulators_pysces-0.1.33.dist-info/LICENSE
biosimulators_pysces-0.1.33.dist-info/METADATA
biosimulators_pysces-0.1.33.dist-info/WHEEL
biosimulators_pysces-0.1.33.dist-info/entry_points.txt
biosimulators_pysces-0.1.33.dist-info/top_level.txt
biosimulators_pysces-0.1.33.dist-info/RECORD
