Metadata-Version: 2.1
Name: biosimulators_pysces
Version: 0.1.33
Summary: BioSimulators-compliant command-line interface to the PySCeS simulation program <http://pysces.sourceforge.net/>.
Home-page: https://github.com/biosimulators/Biosimulators_PySCeS>
Download-URL: https://github.com/biosimulators/Biosimulators_PySCeS
Author: Center for Reproducible Biomedical Modeling
Author-email: info@biosimulators.org
License: MIT
Keywords: BioSimulators,systems biology,computational biology,mathematical model,kinetic model,simulation,SBML,SED-ML,COMBINE,OMEX
Classifier: Development Status :: 3 - Alpha
Classifier: Intended Audience :: Science/Research
Classifier: License :: OSI Approved :: MIT License
Classifier: Topic :: Scientific/Engineering :: Bio-Informatics
License-File: LICENSE
Requires-Dist: biosimulators-utils[logging,sbml]>=0.1.180
Requires-Dist: kisao>=2.32
Requires-Dist: lxml
Requires-Dist: numpy
Requires-Dist: pysces[parscan,sbml]>=1.0.0
Provides-Extra: all
Requires-Dist: biosimulators-utils[containers]; extra == "all"
Requires-Dist: python-dateutil; extra == "all"
Provides-Extra: docs
Provides-Extra: tests
Requires-Dist: biosimulators-utils[containers]; extra == "tests"
Requires-Dist: python-dateutil; extra == "tests"
